"Method, Nodes, Cyclomatic Complexity
"
"net/sf/freecol/tools/SaveGameValidator.<init>, digraph cfg{
""IF_ICMPGE43""->""LABEL39""
""IF_ICMPGE43""->""LINENUMBER 55180""
""IF_ICMPGE43""->""ALOAD181""
""IF_ICMPGE43""->""INVOKEVIRTUAL(exists)182""
""IF_ICMPGE43""->""IFEQ183""
""IF_ICMPGE43""->""LABEL185""
""IF_ICMPGE43""->""LINENUMBER 53186""
""IF_ICMPGE43""->""FRAME187""
""IF_ICMPGE43""->""IINC188""
""IF_ICMPGE43""->""GOTO189""
""IF_ICMPGE43""->""ILOAD169""
""IF_ICMPGE43""->""FRAME40""
""IF_ICMPGE43""->""ILOAD41""
""IF_ICMPGE43""->""ILOAD42""
""IF_ICMPGE43""->""ALOAD44""
""IF_ICMPGE43""->""AALOAD170""
""IF_ICMPGE43""->""ASTORE171""
""IF_ICMPGE43""->""LABEL172""
""IF_ICMPGE43""->""LINENUMBER 54173""
""IF_ICMPGE43""->""NEW174""
""IF_ICMPGE43""->""DUP175""
""IF_ICMPGE43""->""ALOAD176""
""IF_ICMPGE43""->""INVOKESPECIAL(<init>)177""
""IF_ICMPGE43""->""ASTORE178""
""IF_ICMPGE43""->""LABEL179""
""IFEQ183""->""LINENUMBER 56190""
""IFEQ183""->""ALOAD191""
""IFEQ183""->""INVOKEVIRTUAL(isDirectory)192""
""IFEQ183""->""IFEQ193""
""IFEQ183""->""LABEL184""
""IFEQ59""->""FRAME56""
""IFEQ59""->""ALOAD57""
""IFEQ59""->""INVOKEINTERFACE(hasNext)58""
""IFEQ59""->""INVOKEVIRTUAL(append)160""
""IFEQ59""->""ALOAD161""
""IFEQ59""->""DUP140""
""IFEQ59""->""INVOKEVIRTUAL(getName)162""
""IFEQ59""->""ALOAD141""
""IFEQ59""->""INVOKEVIRTUAL(append)163""
""IFEQ59""->""INVOKESPECIAL(<init>)142""
""IFEQ59""->""INVOKEVIRTUAL(toString)164""
""IFEQ59""->""ASTORE143""
""IFEQ59""->""INVOKEVIRTUAL(println)165""
""IFEQ59""->""LABEL144""
""IFEQ59""->""LABEL166""
""IFEQ59""->""LINENUMBER 69145""
""IFEQ59""->""LINENUMBER 79167""
""IFEQ59""->""ALOAD146""
""IFEQ59""->""GOTO168""
""IFEQ59""->""NEW147""
""IFEQ59""->""DUP148""
""IFEQ59""->""ALOAD149""
""IFEQ59""->""ALOAD60""
""IFEQ59""->""INVOKEINTERFACE(next)69""
""IFEQ59""->""INVOKEVIRTUAL(getSavegameInputStream)150""
""IFEQ59""->""INVOKESPECIAL(<init>)151""
""IFEQ59""->""INVOKEVIRTUAL(validate)152""
""IFEQ59""->""LABEL153""
""IFEQ59""->""LINENUMBER 70154""
""IFEQ59""->""GETSTATIC155""
""IFEQ59""->""NEW156""
""IFEQ59""->""DUP157""
""IFEQ59""->""INVOKESPECIAL(<init>)158""
""IFEQ59""->""LDC159""
""IFEQ59""->""NEW139""
""IFEQ59""->""CHECKCAST70""
""IFEQ59""->""ASTORE71""
""IFEQ59""->""LABEL72""
""IFEQ59""->""LINENUMBER 6873""
""IFEQ59""->""LABEL95""
""IFEQ59""->""LINENUMBER 8096""
""IFEQ59""->""FRAME97""
""IFEQ59""->""GOTO98""
""IFEQ59""->""LABEL55""
""IFEQ193""->""LABEL194""
""IFEQ193""->""LABEL195""
""IFEQ193""->""LINENUMBER 58196""
""IFEQ193""->""FRAME197""
""IFEQ193""->""GETSTATIC198""
""IFEQ193""->""ALOAD210""
""IFEQ193""->""ALOAD199""
""IFEQ193""->""INVOKESTATIC(getSavegameFileList)211""
""IFEQ193""->""INVOKEINTERFACE(test)200""
""IFEQ193""->""INVOKEINTERFACE(addAll)212""
""IFEQ193""->""IFEQ201""
""IFEQ193""->""POP213""
""IFEQ193""->""GOTO214""
""IFEQ193""->""LINENUMBER 57208""
""IFEQ193""->""ALOAD209""
""IFEQ201""->""LABEL202""
""IFEQ201""->""LINENUMBER 59203""
""IFEQ201""->""ALOAD204""
""IFEQ201""->""ALOAD205""
""IFEQ201""->""INVOKEINTERFACE(add)206""
""IFEQ201""->""POP207""
""Entry""->""LABEL78""
""Entry""->""LINENUMBER 7779""
""Entry""->""LINENUMBER 71100""
""Entry""->""FRAME101""
""Entry""->""ASTORE102""
""Entry""->""LABEL103""
""Entry""->""LINENUMBER 72104""
""Entry""->""GETSTATIC105""
""Entry""->""NEW106""
""Entry""->""GETSTATIC80""
""Entry""->""DUP107""
""Entry""->""NEW81""
""Entry""->""INVOKESPECIAL(<init>)108""
""Entry""->""DUP82""
""Entry""->""ALOAD109""
""Entry""->""INVOKESPECIAL(<init>)83""
""Entry""->""LDC84""
""Entry""->""INVOKEVIRTUAL(append)85""
""Entry""->""ALOAD86""
""Entry""->""INVOKEVIRTUAL(getName)87""
""Entry""->""INVOKEVIRTUAL(append)88""
""Entry""->""INVOKEVIRTUAL(toString)89""
""Entry""->""INVOKEVIRTUAL(getMessage)110""
""Entry""->""INVOKEVIRTUAL(append)111""
""Entry""->""LDC112""
""Entry""->""INVOKEVIRTUAL(append)113""
""Entry""->""ALOAD114""
""Entry""->""LABEL115""
""Entry""->""LINENUMBER 73116""
""Entry""->""INVOKEVIRTUAL(println)90""
""Entry""->""INVOKEVIRTUAL(getLineNumber)117""
""Entry""->""LABEL91""
""Entry""->""INVOKEVIRTUAL(append)118""
""Entry""->""LINENUMBER 7892""
""Entry""->""LDC119""
""Entry""->""ICONST_293""
""Entry""->""ISTORE94""
""Entry""->""LABEL95""
""Entry""->""LINENUMBER 8096""
""Entry""->""FRAME97""
""Entry""->""LDC10""
""Entry""->""GOTO98""
""Entry""->""INVOKESPECIAL(<init>)11""
""Entry""->""LABEL99""
""Entry""->""ASTORE12""
""Entry""->""LABEL13""
""Entry""->""LINENUMBER 4914""
""Entry""->""ALOAD15""
""Entry""->""ALOAD16""
""Entry""->""INVOKEVIRTUAL(newSchema)17""
""Entry""->""ASTORE18""
""Entry""->""LABEL19""
""Entry""->""INVOKEVIRTUAL(append)120""
""Entry""->""ALOAD121""
""Entry""->""LABEL1""
""Entry""->""LABEL122""
""Entry""->""LINENUMBER 472""
""Entry""->""LINENUMBER 74123""
""Entry""->""LDC3""
""Entry""->""INVOKEVIRTUAL(getColumnNumber)124""
""Entry""->""INVOKESTATIC(newInstance)4""
""Entry""->""INVOKEVIRTUAL(append)125""
""Entry""->""ASTORE5""
""Entry""->""INVOKEVIRTUAL(toString)126""
""Entry""->""LABEL6""
""Entry""->""LABEL127""
""Entry""->""LINENUMBER 487""
""Entry""->""LINENUMBER 72128""
""Entry""->""NEW8""
""Entry""->""INVOKEVIRTUAL(println)129""
""Entry""->""DUP9""
""Entry""->""LINENUMBER 5020""
""Entry""->""ALOAD21""
""Entry""->""INVOKEVIRTUAL(newValidator)22""
""Entry""->""ASTORE23""
""Entry""->""LABEL24""
""Entry""->""LINENUMBER 5225""
""Entry""->""NEW26""
""Entry""->""DUP27""
""Entry""->""INVOKESPECIAL(<init>)28""
""Entry""->""ASTORE29""
""Entry""->""LABEL130""
""Entry""->""LINENUMBER 75131""
""Entry""->""ILOAD132""
""Entry""->""ICONST_1133""
""Entry""->""INVOKESTATIC(max)134""
""Entry""->""ISTORE135""
""Entry""->""LABEL136""
""Entry""->""LINENUMBER 79137""
""Entry""->""GOTO138""
""Entry""->""LABEL30""
""Entry""->""LINENUMBER 5331""
""Entry""->""ALOAD32""
""Entry""->""ASTORE33""
""Entry""->""ALOAD34""
""Entry""->""ARRAYLENGTH35""
""Entry""->""ISTORE36""
""Entry""->""ICONST_037""
""Entry""->""ISTORE38""
""Entry""->""LABEL39""
""Entry""->""FRAME40""
""Entry""->""ILOAD41""
""Entry""->""ILOAD42""
""Entry""->""IF_ICMPGE43""
""Entry""->""LABEL45""
""Entry""->""LINENUMBER 6446""
""Entry""->""FRAME47""
""Entry""->""ICONST_048""
""Entry""->""ISTORE49""
""Entry""->""LABEL50""
""Entry""->""LINENUMBER 6551""
""Entry""->""ALOAD52""
""Entry""->""INVOKEINTERFACE(iterator)53""
""Entry""->""ASTORE54""
""Entry""->""IFEQ59""
""Entry""->""LABEL61""
""Entry""->""LINENUMBER 8162""
""Entry""->""FRAME63""
""Entry""->""ILOAD64""
""Entry""->""INVOKESTATIC(exit)65""
""Entry""->""LABEL66""
""Entry""->""LINENUMBER 8267""
""Entry""->""RETURN68""
""Entry""->""Exit""
""Entry""->""LABEL74""
""Entry""->""LINENUMBER 7675""
""Entry""->""FRAME76""
""Entry""->""ASTORE77""
}.{{null""Entry"",""LABEL1"",""LINENUMBER 432"",""ALOAD3"",""INVOKESPECIAL(<init>)4"",""RETURN5"",""Exit"",}""IF_ICMPGE43"",""LABEL39"",""LINENUMBER 55180"",""ALOAD181"",""INVOKEVIRTUAL(exists)182"",""IFEQ183"",""LABEL185"",""LINENUMBER 53186"",""FRAME187"",""IINC188"",""GOTO189"",""ILOAD169"",""FRAME40"",""ILOAD41"",""ILOAD42"",""ALOAD44"",""AALOAD170"",""ASTORE171"",""LABEL172"",""LINENUMBER 54173"",""NEW174"",""DUP175"",""ALOAD176"",""INVOKESPECIAL(<init>)177"",""ASTORE178"",""LABEL179"",""IFEQ59"",""FRAME56"",""ALOAD57"",""INVOKEINTERFACE(hasNext)58"",""INVOKEVIRTUAL(append)160"",""ALOAD161"",""DUP140"",""INVOKEVIRTUAL(getName)162"",""ALOAD141"",""INVOKEVIRTUAL(append)163"",""INVOKESPECIAL(<init>)142"",""INVOKEVIRTUAL(toString)164"",""ASTORE143"",""INVOKEVIRTUAL(println)165"",""LABEL144"",""LABEL166"",""LINENUMBER 69145"",""LINENUMBER 79167"",""ALOAD146"",""GOTO168"",""NEW147"",""DUP148"",""ALOAD149"",""ALOAD60"",""INVOKEINTERFACE(next)69"",""INVOKEVIRTUAL(getSavegameInputStream)150"",""INVOKESPECIAL(<init>)151"",""INVOKEVIRTUAL(validate)152"",""LABEL153"",""LINENUMBER 70154"",""GETSTATIC155"",""NEW156"",""DUP157"",""INVOKESPECIAL(<init>)158"",""LDC159"",""NEW139"",""CHECKCAST70"",""ASTORE71"",""LABEL72"",""LINENUMBER 6873"",""LABEL95"",""LINENUMBER 8096"",""FRAME97"",""GOTO98"",""LABEL55"",""LINENUMBER 56190"",""ALOAD191"",""INVOKEVIRTUAL(isDirectory)192"",""IFEQ193"",""LABEL184"",""ALOAD210"",""INVOKESTATIC(getSavegameFileList)211"",""INVOKEINTERFACE(addAll)212"",""POP213"",""GOTO214"",""LINENUMBER 57208"",""ALOAD209"",""LABEL194"",""ALOAD199"",""INVOKEINTERFACE(test)200"",""IFEQ201"",""LABEL195"",""LINENUMBER 58196"",""FRAME197"",""GETSTATIC198"",""LABEL202"",""LINENUMBER 59203"",""ALOAD204"",""ALOAD205"",""INVOKEINTERFACE(add)206"",""POP207"",""Entry"",""ALOAD34"",""ARRAYLENGTH35"",""ISTORE36"",""ICONST_037"",""ISTORE38"",""LABEL45"",""LINENUMBER 6446"",""FRAME47"",""ICONST_048"",""ISTORE49"",""LABEL50"",""LINENUMBER 6551"",""ALOAD52"",""INVOKEINTERFACE(iterator)53"",""LDC10"",""ASTORE54"",""INVOKESPECIAL(<init>)11"",""ASTORE12"",""LABEL13"",""LINENUMBER 4914"",""ALOAD15"",""ALOAD16"",""INVOKEVIRTUAL(newSchema)17"",""ASTORE18"",""LABEL19"",""LABEL1"",""LINENUMBER 472"",""LDC3"",""INVOKESTATIC(newInstance)4"",""ASTORE5"",""LABEL6"",""LINENUMBER 487"",""NEW8"",""DUP9"",""LINENUMBER 5020"",""ALOAD21"",""INVOKEVIRTUAL(newValidator)22"",""ASTORE23"",""LABEL24"",""LINENUMBER 5225"",""NEW26"",""DUP27"",""INVOKESPECIAL(<init>)28"",""ASTORE29"",""LABEL30"",""LINENUMBER 5331"",""ALOAD32"",""ASTORE33"",""LABEL78"",""LINENUMBER 7779"",""GETSTATIC80"",""NEW81"",""DUP82"",""INVOKESPECIAL(<init>)83"",""LDC84"",""INVOKEVIRTUAL(append)85"",""ALOAD86"",""INVOKEVIRTUAL(getName)87"",""INVOKEVIRTUAL(append)88"",""INVOKEVIRTUAL(toString)89"",""INVOKEVIRTUAL(println)90"",""LABEL91"",""LINENUMBER 7892"",""ICONST_293"",""ISTORE94"",""LABEL74"",""LINENUMBER 7675"",""FRAME76"",""ASTORE77"",""INVOKEVIRTUAL(append)120"",""ALOAD121"",""LINENUMBER 71100"",""LABEL122"",""FRAME101"",""LINENUMBER 74123"",""ASTORE102"",""INVOKEVIRTUAL(getColumnNumber)124"",""LABEL103"",""INVOKEVIRTUAL(append)125"",""LINENUMBER 72104"",""INVOKEVIRTUAL(toString)126"",""GETSTATIC105"",""LABEL127"",""NEW106"",""LINENUMBER 72128"",""DUP107"",""INVOKEVIRTUAL(println)129"",""INVOKESPECIAL(<init>)108"",""ALOAD109"",""LABEL130"",""LINENUMBER 75131"",""INVOKEVIRTUAL(getMessage)110"",""ILOAD132"",""INVOKEVIRTUAL(append)111"",""ICONST_1133"",""LDC112"",""INVOKESTATIC(max)134"",""INVOKEVIRTUAL(append)113"",""ISTORE135"",""ALOAD114"",""LABEL136"",""LABEL115"",""LINENUMBER 79137"",""LINENUMBER 73116"",""GOTO138"",""INVOKEVIRTUAL(getLineNumber)117"",""INVOKEVIRTUAL(append)118"",""LDC119"",""LABEL99"",""LABEL61"",""LINENUMBER 8162"",""FRAME63"",""ILOAD64"",""INVOKESTATIC(exit)65"",""LABEL66"",""LINENUMBER 8267"",""RETURN68"",""Exit"",} . 0.005076142131979695 . 1.0 . 7, 1
"
"net/sf/freecol/tools/SaveGameValidator.main, digraph cfg{
""IF_ICMPGE43""->""LABEL39""
""IF_ICMPGE43""->""LINENUMBER 55180""
""IF_ICMPGE43""->""ALOAD181""
""IF_ICMPGE43""->""INVOKEVIRTUAL(exists)182""
""IF_ICMPGE43""->""IFEQ183""
""IF_ICMPGE43""->""LABEL185""
""IF_ICMPGE43""->""LINENUMBER 53186""
""IF_ICMPGE43""->""FRAME187""
""IF_ICMPGE43""->""IINC188""
""IF_ICMPGE43""->""GOTO189""
""IF_ICMPGE43""->""ILOAD169""
""IF_ICMPGE43""->""FRAME40""
""IF_ICMPGE43""->""ILOAD41""
""IF_ICMPGE43""->""ILOAD42""
""IF_ICMPGE43""->""ALOAD44""
""IF_ICMPGE43""->""AALOAD170""
""IF_ICMPGE43""->""ASTORE171""
""IF_ICMPGE43""->""LABEL172""
""IF_ICMPGE43""->""LINENUMBER 54173""
""IF_ICMPGE43""->""NEW174""
""IF_ICMPGE43""->""DUP175""
""IF_ICMPGE43""->""ALOAD176""
""IF_ICMPGE43""->""INVOKESPECIAL(<init>)177""
""IF_ICMPGE43""->""ASTORE178""
""IF_ICMPGE43""->""LABEL179""
""IFEQ183""->""LINENUMBER 56190""
""IFEQ183""->""ALOAD191""
""IFEQ183""->""INVOKEVIRTUAL(isDirectory)192""
""IFEQ183""->""IFEQ193""
""IFEQ183""->""LABEL184""
""IFEQ59""->""FRAME56""
""IFEQ59""->""ALOAD57""
""IFEQ59""->""INVOKEINTERFACE(hasNext)58""
""IFEQ59""->""INVOKEVIRTUAL(append)160""
""IFEQ59""->""ALOAD161""
""IFEQ59""->""DUP140""
""IFEQ59""->""INVOKEVIRTUAL(getName)162""
""IFEQ59""->""ALOAD141""
""IFEQ59""->""INVOKEVIRTUAL(append)163""
""IFEQ59""->""INVOKESPECIAL(<init>)142""
""IFEQ59""->""INVOKEVIRTUAL(toString)164""
""IFEQ59""->""ASTORE143""
""IFEQ59""->""INVOKEVIRTUAL(println)165""
""IFEQ59""->""LABEL144""
""IFEQ59""->""LABEL166""
""IFEQ59""->""LINENUMBER 69145""
""IFEQ59""->""LINENUMBER 79167""
""IFEQ59""->""ALOAD146""
""IFEQ59""->""GOTO168""
""IFEQ59""->""NEW147""
""IFEQ59""->""DUP148""
""IFEQ59""->""ALOAD149""
""IFEQ59""->""ALOAD60""
""IFEQ59""->""INVOKEINTERFACE(next)69""
""IFEQ59""->""INVOKEVIRTUAL(getSavegameInputStream)150""
""IFEQ59""->""INVOKESPECIAL(<init>)151""
""IFEQ59""->""INVOKEVIRTUAL(validate)152""
""IFEQ59""->""LABEL153""
""IFEQ59""->""LINENUMBER 70154""
""IFEQ59""->""GETSTATIC155""
""IFEQ59""->""NEW156""
""IFEQ59""->""DUP157""
""IFEQ59""->""INVOKESPECIAL(<init>)158""
""IFEQ59""->""LDC159""
""IFEQ59""->""NEW139""
""IFEQ59""->""CHECKCAST70""
""IFEQ59""->""ASTORE71""
""IFEQ59""->""LABEL72""
""IFEQ59""->""LINENUMBER 6873""
""IFEQ59""->""LABEL95""
""IFEQ59""->""LINENUMBER 8096""
""IFEQ59""->""FRAME97""
""IFEQ59""->""GOTO98""
""IFEQ59""->""LABEL55""
""IFEQ193""->""LABEL194""
""IFEQ193""->""LABEL195""
""IFEQ193""->""LINENUMBER 58196""
""IFEQ193""->""FRAME197""
""IFEQ193""->""GETSTATIC198""
""IFEQ193""->""ALOAD210""
""IFEQ193""->""ALOAD199""
""IFEQ193""->""INVOKESTATIC(getSavegameFileList)211""
""IFEQ193""->""INVOKEINTERFACE(test)200""
""IFEQ193""->""INVOKEINTERFACE(addAll)212""
""IFEQ193""->""IFEQ201""
""IFEQ193""->""POP213""
""IFEQ193""->""GOTO214""
""IFEQ193""->""LINENUMBER 57208""
""IFEQ193""->""ALOAD209""
""IFEQ201""->""LABEL202""
""IFEQ201""->""LINENUMBER 59203""
""IFEQ201""->""ALOAD204""
""IFEQ201""->""ALOAD205""
""IFEQ201""->""INVOKEINTERFACE(add)206""
""IFEQ201""->""POP207""
""Entry""->""LABEL78""
""Entry""->""LINENUMBER 7779""
""Entry""->""LINENUMBER 71100""
""Entry""->""FRAME101""
""Entry""->""ASTORE102""
""Entry""->""LABEL103""
""Entry""->""LINENUMBER 72104""
""Entry""->""GETSTATIC105""
""Entry""->""NEW106""
""Entry""->""GETSTATIC80""
""Entry""->""DUP107""
""Entry""->""NEW81""
""Entry""->""INVOKESPECIAL(<init>)108""
""Entry""->""DUP82""
""Entry""->""ALOAD109""
""Entry""->""INVOKESPECIAL(<init>)83""
""Entry""->""LDC84""
""Entry""->""INVOKEVIRTUAL(append)85""
""Entry""->""ALOAD86""
""Entry""->""INVOKEVIRTUAL(getName)87""
""Entry""->""INVOKEVIRTUAL(append)88""
""Entry""->""INVOKEVIRTUAL(toString)89""
""Entry""->""INVOKEVIRTUAL(getMessage)110""
""Entry""->""INVOKEVIRTUAL(append)111""
""Entry""->""LDC112""
""Entry""->""INVOKEVIRTUAL(append)113""
""Entry""->""ALOAD114""
""Entry""->""LABEL115""
""Entry""->""LINENUMBER 73116""
""Entry""->""INVOKEVIRTUAL(println)90""
""Entry""->""INVOKEVIRTUAL(getLineNumber)117""
""Entry""->""LABEL91""
""Entry""->""INVOKEVIRTUAL(append)118""
""Entry""->""LINENUMBER 7892""
""Entry""->""LDC119""
""Entry""->""ICONST_293""
""Entry""->""ISTORE94""
""Entry""->""LABEL95""
""Entry""->""LINENUMBER 8096""
""Entry""->""FRAME97""
""Entry""->""LDC10""
""Entry""->""GOTO98""
""Entry""->""INVOKESPECIAL(<init>)11""
""Entry""->""LABEL99""
""Entry""->""ASTORE12""
""Entry""->""LABEL13""
""Entry""->""LINENUMBER 4914""
""Entry""->""ALOAD15""
""Entry""->""ALOAD16""
""Entry""->""INVOKEVIRTUAL(newSchema)17""
""Entry""->""ASTORE18""
""Entry""->""LABEL19""
""Entry""->""INVOKEVIRTUAL(append)120""
""Entry""->""ALOAD121""
""Entry""->""LABEL1""
""Entry""->""LABEL122""
""Entry""->""LINENUMBER 472""
""Entry""->""LINENUMBER 74123""
""Entry""->""LDC3""
""Entry""->""INVOKEVIRTUAL(getColumnNumber)124""
""Entry""->""INVOKESTATIC(newInstance)4""
""Entry""->""INVOKEVIRTUAL(append)125""
""Entry""->""ASTORE5""
""Entry""->""INVOKEVIRTUAL(toString)126""
""Entry""->""LABEL6""
""Entry""->""LABEL127""
""Entry""->""LINENUMBER 487""
""Entry""->""LINENUMBER 72128""
""Entry""->""NEW8""
""Entry""->""INVOKEVIRTUAL(println)129""
""Entry""->""DUP9""
""Entry""->""LINENUMBER 5020""
""Entry""->""ALOAD21""
""Entry""->""INVOKEVIRTUAL(newValidator)22""
""Entry""->""ASTORE23""
""Entry""->""LABEL24""
""Entry""->""LINENUMBER 5225""
""Entry""->""NEW26""
""Entry""->""DUP27""
""Entry""->""INVOKESPECIAL(<init>)28""
""Entry""->""ASTORE29""
""Entry""->""LABEL130""
""Entry""->""LINENUMBER 75131""
""Entry""->""ILOAD132""
""Entry""->""ICONST_1133""
""Entry""->""INVOKESTATIC(max)134""
""Entry""->""ISTORE135""
""Entry""->""LABEL136""
""Entry""->""LINENUMBER 79137""
""Entry""->""GOTO138""
""Entry""->""LABEL30""
""Entry""->""LINENUMBER 5331""
""Entry""->""ALOAD32""
""Entry""->""ASTORE33""
""Entry""->""ALOAD34""
""Entry""->""ARRAYLENGTH35""
""Entry""->""ISTORE36""
""Entry""->""ICONST_037""
""Entry""->""ISTORE38""
""Entry""->""LABEL39""
""Entry""->""FRAME40""
""Entry""->""ILOAD41""
""Entry""->""ILOAD42""
""Entry""->""IF_ICMPGE43""
""Entry""->""LABEL45""
""Entry""->""LINENUMBER 6446""
""Entry""->""FRAME47""
""Entry""->""ICONST_048""
""Entry""->""ISTORE49""
""Entry""->""LABEL50""
""Entry""->""LINENUMBER 6551""
""Entry""->""ALOAD52""
""Entry""->""INVOKEINTERFACE(iterator)53""
""Entry""->""ASTORE54""
""Entry""->""IFEQ59""
""Entry""->""LABEL61""
""Entry""->""LINENUMBER 8162""
""Entry""->""FRAME63""
""Entry""->""ILOAD64""
""Entry""->""INVOKESTATIC(exit)65""
""Entry""->""LABEL66""
""Entry""->""LINENUMBER 8267""
""Entry""->""RETURN68""
""Entry""->""Exit""
""Entry""->""LABEL74""
""Entry""->""LINENUMBER 7675""
""Entry""->""FRAME76""
""Entry""->""ASTORE77""
}.{{null""Entry"",""LABEL1"",""LINENUMBER 432"",""ALOAD3"",""INVOKESPECIAL(<init>)4"",""RETURN5"",""Exit"",}""IF_ICMPGE43"",""LABEL39"",""LINENUMBER 55180"",""ALOAD181"",""INVOKEVIRTUAL(exists)182"",""IFEQ183"",""LABEL185"",""LINENUMBER 53186"",""FRAME187"",""IINC188"",""GOTO189"",""ILOAD169"",""FRAME40"",""ILOAD41"",""ILOAD42"",""ALOAD44"",""AALOAD170"",""ASTORE171"",""LABEL172"",""LINENUMBER 54173"",""NEW174"",""DUP175"",""ALOAD176"",""INVOKESPECIAL(<init>)177"",""ASTORE178"",""LABEL179"",""IFEQ59"",""FRAME56"",""ALOAD57"",""INVOKEINTERFACE(hasNext)58"",""INVOKEVIRTUAL(append)160"",""ALOAD161"",""DUP140"",""INVOKEVIRTUAL(getName)162"",""ALOAD141"",""INVOKEVIRTUAL(append)163"",""INVOKESPECIAL(<init>)142"",""INVOKEVIRTUAL(toString)164"",""ASTORE143"",""INVOKEVIRTUAL(println)165"",""LABEL144"",""LABEL166"",""LINENUMBER 69145"",""LINENUMBER 79167"",""ALOAD146"",""GOTO168"",""NEW147"",""DUP148"",""ALOAD149"",""ALOAD60"",""INVOKEINTERFACE(next)69"",""INVOKEVIRTUAL(getSavegameInputStream)150"",""INVOKESPECIAL(<init>)151"",""INVOKEVIRTUAL(validate)152"",""LABEL153"",""LINENUMBER 70154"",""GETSTATIC155"",""NEW156"",""DUP157"",""INVOKESPECIAL(<init>)158"",""LDC159"",""NEW139"",""CHECKCAST70"",""ASTORE71"",""LABEL72"",""LINENUMBER 6873"",""LABEL95"",""LINENUMBER 8096"",""FRAME97"",""GOTO98"",""LABEL55"",""LINENUMBER 56190"",""ALOAD191"",""INVOKEVIRTUAL(isDirectory)192"",""IFEQ193"",""LABEL184"",""ALOAD210"",""INVOKESTATIC(getSavegameFileList)211"",""INVOKEINTERFACE(addAll)212"",""POP213"",""GOTO214"",""LINENUMBER 57208"",""ALOAD209"",""LABEL194"",""ALOAD199"",""INVOKEINTERFACE(test)200"",""IFEQ201"",""LABEL195"",""LINENUMBER 58196"",""FRAME197"",""GETSTATIC198"",""LABEL202"",""LINENUMBER 59203"",""ALOAD204"",""ALOAD205"",""INVOKEINTERFACE(add)206"",""POP207"",""Entry"",""ALOAD34"",""ARRAYLENGTH35"",""ISTORE36"",""ICONST_037"",""ISTORE38"",""LABEL45"",""LINENUMBER 6446"",""FRAME47"",""ICONST_048"",""ISTORE49"",""LABEL50"",""LINENUMBER 6551"",""ALOAD52"",""INVOKEINTERFACE(iterator)53"",""LDC10"",""ASTORE54"",""INVOKESPECIAL(<init>)11"",""ASTORE12"",""LABEL13"",""LINENUMBER 4914"",""ALOAD15"",""ALOAD16"",""INVOKEVIRTUAL(newSchema)17"",""ASTORE18"",""LABEL19"",""LABEL1"",""LINENUMBER 472"",""LDC3"",""INVOKESTATIC(newInstance)4"",""ASTORE5"",""LABEL6"",""LINENUMBER 487"",""NEW8"",""DUP9"",""LINENUMBER 5020"",""ALOAD21"",""INVOKEVIRTUAL(newValidator)22"",""ASTORE23"",""LABEL24"",""LINENUMBER 5225"",""NEW26"",""DUP27"",""INVOKESPECIAL(<init>)28"",""ASTORE29"",""LABEL30"",""LINENUMBER 5331"",""ALOAD32"",""ASTORE33"",""LABEL78"",""LINENUMBER 7779"",""GETSTATIC80"",""NEW81"",""DUP82"",""INVOKESPECIAL(<init>)83"",""LDC84"",""INVOKEVIRTUAL(append)85"",""ALOAD86"",""INVOKEVIRTUAL(getName)87"",""INVOKEVIRTUAL(append)88"",""INVOKEVIRTUAL(toString)89"",""INVOKEVIRTUAL(println)90"",""LABEL91"",""LINENUMBER 7892"",""ICONST_293"",""ISTORE94"",""LABEL74"",""LINENUMBER 7675"",""FRAME76"",""ASTORE77"",""INVOKEVIRTUAL(append)120"",""ALOAD121"",""LINENUMBER 71100"",""LABEL122"",""FRAME101"",""LINENUMBER 74123"",""ASTORE102"",""INVOKEVIRTUAL(getColumnNumber)124"",""LABEL103"",""INVOKEVIRTUAL(append)125"",""LINENUMBER 72104"",""INVOKEVIRTUAL(toString)126"",""GETSTATIC105"",""LABEL127"",""NEW106"",""LINENUMBER 72128"",""DUP107"",""INVOKEVIRTUAL(println)129"",""INVOKESPECIAL(<init>)108"",""ALOAD109"",""LABEL130"",""LINENUMBER 75131"",""INVOKEVIRTUAL(getMessage)110"",""ILOAD132"",""INVOKEVIRTUAL(append)111"",""ICONST_1133"",""LDC112"",""INVOKESTATIC(max)134"",""INVOKEVIRTUAL(append)113"",""ISTORE135"",""ALOAD114"",""LABEL136"",""LABEL115"",""LINENUMBER 79137"",""LINENUMBER 73116"",""GOTO138"",""INVOKEVIRTUAL(getLineNumber)117"",""INVOKEVIRTUAL(append)118"",""LDC119"",""LABEL99"",""LABEL61"",""LINENUMBER 8162"",""FRAME63"",""ILOAD64"",""INVOKESTATIC(exit)65"",""LABEL66"",""LINENUMBER 8267"",""RETURN68"",""Exit"",} . 0.005076142131979695 . 1.0 . 216, 7
"
